topo_parse_mcp/__init__.py
topo_parse_mcp/utils/globals.py
topo_parse_mcp/utils/graph_db.py
topo_parse_mcp/utils/json_tools.py
topo_parse_mcp/utils/log_output.py
topo_parse_mcp/utils/topo_graph.py
topo_parse_mcp-0.1.0.dist-info/WHEEL
topo_parse_mcp-0.1.0.dist-info/entry_points.txt
topo_parse_mcp-0.1.0.dist-info/METADATA
topo_parse_mcp-0.1.0.dist-info/RECORD
